{
  "CA": [
    {
      "name": "Alameda",
      "key": "Geometry.Alameda"
    },
    {
      "name": "Alpine",
      "key": "Geometry.Alpine"
    },
    {
      "name": "Amador",
      "key": "Geometry.Amador"
    },
    {
      "name": "Butte",
      "key": "Geometry.Butte"
    },
    {
      "name": "Calaveras",
      "key": "Geometry.Calaveras"
    },
    {
      "name": "Colusa",
      "key": "Geometry.Colusa"
    },
    {
      "name": "Contra Costa",
      "key": "Geometry.ContraCosta"
    },
    {
      "name": "Del Norte",
      "key": "Geometry.DelNorte"
    },
    {
      "name": "El Dorado",
      "key": "Geometry.ElDorado"
    },
    {
      "name": "Fresno",
      "key": "Geometry.Fresno"
    },
    {
      "name": "Glenn",
      "key": "Geometry.Glenn"
    },
    {
      "name": "Humboldt",
      "key": "Geometry.Humboldt"
    },
    {
      "name": "Imperial",
      "key": "Geometry.Imperial"
    },
    {
      "name": "Inyo",
      "key": "Geometry.Inyo"
    },
    {
      "name": "Kern",
      "key": "Geometry.Kern"
    },
    {
      "name": "Kings",
      "key": "Geometry.Kings"
    },
    {
      "name": "Lake",
      "key": "Geometry.Lake"
    },
    {
      "name": "Lassen",
      "key": "Geometry.Lassen"
    },
    {
      "name": "Los Angeles",
      "key": "Geometry.LosAngeles"
    },
    {
      "name": "Madera",
      "key": "Geometry.Madera"
    },
    {
      "name": "Marin",
      "key": "Geometry.Marin"
    },
    {
      "name": "Mariposa",
      "key": "Geometry.Mariposa"
    },
    {
      "name": "Mendocino",
      "key": "Geometry.Mendocino"
    },
    {
      "name": "Merced",
      "key": "Geometry.Merced"
    },
    {
      "name": "Modoc",
      "key": "Geometry.Modoc"
    },
    {
      "name": "Mono",
      "key": "Geometry.Mono"
    },
    {
      "name": "Monterey",
      "key": "Geometry.Monterey"
    },
    {
      "name": "Napa",
      "key": "Geometry.Napa"
    },
    {
      "name": "Nevada",
      "key": "Geometry.Nevada"
    },
    {
      "name": "Orange",
      "key": "Geometry.Orange"
    },
    {
      "name": "Placer",
      "key": "Geometry.Placer"
    },
    {
      "name": "Plumas",
      "key": "Geometry.Plumas"
    },
    {
      "name": "Riverside",
      "key": "Geometry.Riverside"
    },
    {
      "name": "Sacramento",
      "key": "Geometry.Sacramento"
    },
    {
      "name": "San Benito",
      "key": "Geometry.SanBenito"
    },
    {
      "name": "San Bernardino",
      "key": "Geometry.SanBernardino"
    },
    {
      "name": "San Diego",
      "key": "Geometry.SanDiego"
    },
    {
      "name": "San Francisco",
      "key": "Geometry.SanFrancisco"
    },
    {
      "name": "San Joaquin",
      "key": "Geometry.SanJoaquin"
    },
    {
      "name": "San Luis Obispo",
      "key": "Geometry.SanLuisObispo"
    },
    {
      "name": "San Mateo",
      "key": "Geometry.SanMateo"
    },
    {
      "name": "Santa Barbara",
      "key": "Geometry.SantaBarbara"
    },
    {
      "name": "Santa Clara",
      "key": "Geometry.SantaClara"
    },
    {
      "name": "Santa Cruz",
      "key": "Geometry.SantaCruz"
    },
    {
      "name": "Shasta",
      "key": "Geometry.Shasta"
    },
    {
      "name": "Sierra",
      "key": "Geometry.Sierra"
    },
    {
      "name": "Siskiyou",
      "key": "Geometry.Siskiyou"
    },
    {
      "name": "Solano",
      "key": "Geometry.Solano"
    },
    {
      "name": "Sonoma",
      "key": "Geometry.Sonoma"
    },
    {
      "name": "Stanislaus",
      "key": "Geometry.Stanislaus"
    },
    {
      "name": "Sutter",
      "key": "Geometry.Sutter"
    },
    {
      "name": "Tehama",
      "key": "Geometry.Tehama"
    },
    {
      "name": "Trinity",
      "key": "Geometry.Trinity"
    },
    {
      "name": "Tulare",
      "key": "Geometry.Tulare"
    },
    {
      "name": "Tuolumne",
      "key": "Geometry.Tuolumne"
    },
    {
      "name": "Ventura",
      "key": "Geometry.Ventura"
    },
    {
      "name": "Yolo",
      "key": "Geometry.Yolo"
    },
    {
      "name": "Yuba",
      "key": "Geometry.Yuba"
    }
  ],
  "FL": [
    {
      "name": "Alachua",
      "key": "Geometry.Alachua"
    },
    {
      "name": "Baker",
      "key": "Geometry.Baker"
    },
    {
      "name": "Bay",
      "key": "Geometry.Bay"
    },
    {
      "name": "Bradford",
      "key": "Geometry.Bradford"
    },
    {
      "name": "Brevard",
      "key": "Geometry.Brevard"
    },
    {
      "name": "Broward",
      "key": "Geometry.Broward"
    },
    {
      "name": "Calhoun",
      "key": "Geometry.Calhoun"
    },
    {
      "name": "Charlotte",
      "key": "Geometry.Charlotte"
    },
    {
      "name": "Citrus",
      "key": "Geometry.Citrus"
    },
    {
      "name": "Clay",
      "key": "Geometry.Clay"
    },
    {
      "name": "Collier",
      "key": "Geometry.Collier"
    },
    {
      "name": "Columbia",
      "key": "Geometry.Columbia"
    },
    {
      "name": "DeSoto",
      "key": "Geometry.DeSoto"
    },
    {
      "name": "Dixie",
      "key": "Geometry.Dixie"
    },
    {
      "name": "Duval",
      "key": "Geometry.Duval"
    },
    {
      "name": "Escambia",
      "key": "Geometry.Escambia"
    },
    {
      "name": "Flagler",
      "key": "Geometry.Flagler"
    },
    {
      "name": "Franklin",
      "key": "Geometry.Franklin"
    },
    {
      "name": "Gadsden",
      "key": "Geometry.Gadsden"
    },
    {
      "name": "Gilchrist",
      "key": "Geometry.Gilchrist"
    },
    {
      "name": "Glades",
      "key": "Geometry.Glades"
    },
    {
      "name": "Gulf",
      "key": "Geometry.Gulf"
    },
    {
      "name": "Hamilton",
      "key": "Geometry.Hamilton"
    },
    {
      "name": "Hardee",
      "key": "Geometry.Hardee"
    },
    {
      "name": "Hendry",
      "key": "Geometry.Hendry"
    },
    {
      "name": "Hernando",
      "key": "Geometry.Hernando"
    },
    {
      "name": "Highlands",
      "key": "Geometry.Highlands"
    },
    {
      "name": "Hillsborough",
      "key": "Geometry.Hillsborough"
    },
    {
      "name": "Holmes",
      "key": "Geometry.Holmes"
    },
    {
      "name": "Indian River",
      "key": "Geometry.IndianRiver"
    },
    {
      "name": "Jackson",
      "key": "Geometry.Jackson"
    },
    {
      "name": "Jefferson",
      "key": "Geometry.Jefferson"
    },
    {
      "name": "Lafayette",
      "key": "Geometry.Lafayette"
    },
    {
      "name": "Lake",
      "key": "Geometry.Lake"
    },
    {
      "name": "Lee",
      "key": "Geometry.Lee"
    },
    {
      "name": "Leon",
      "key": "Geometry.Leon"
    },
    {
      "name": "Levy",
      "key": "Geometry.Levy"
    },
    {
      "name": "Liberty",
      "key": "Geometry.Liberty"
    },
    {
      "name": "Madison",
      "key": "Geometry.Madison"
    },
    {
      "name": "Manatee",
      "key": "Geometry.Manatee"
    },
    {
      "name": "Marion",
      "key": "Geometry.Marion"
    },
    {
      "name": "Martin",
      "key": "Geometry.Martin"
    },
    {
      "name": "Miami-Dade",
      "key": "Geometry.MiamiDade"
    },
    {
      "name": "Monroe",
      "key": "Geometry.Monroe"
    },
    {
      "name": "Nassau",
      "key": "Geometry.Nassau"
    },
    {
      "name": "Okaloosa",
      "key": "Geometry.Okaloosa"
    },
    {
      "name": "Okeechobee",
      "key": "Geometry.Okeechobee"
    },
    {
      "name": "Orange",
      "key": "Geometry.Orange"
    },
    {
      "name": "Osceola",
      "key": "Geometry.Osceola"
    },
    {
      "name": "Palm Beach",
      "key": "Geometry.PalmBeach"
    },
    {
      "name": "Pasco",
      "key": "Geometry.Pasco"
    },
    {
      "name": "Pinellas",
      "key": "Geometry.Pinellas"
    },
    {
      "name": "Polk",
      "key": "Geometry.Polk"
    },
    {
      "name": "Putnam",
      "key": "Geometry.Putnam"
    },
    {
      "name": "Santa Rosa",
      "key": "Geometry.SantaRosa"
    },
    {
      "name": "Sarasota",
      "key": "Geometry.Sarasota"
    },
    {
      "name": "Seminole",
      "key": "Geometry.Seminole"
    },
    {
      "name": "St. Johns",
      "key": "Geometry.StJohns"
    },
    {
      "name": "St. Lucie",
      "key": "Geometry.StLucie"
    },
    {
      "name": "Sumter",
      "key": "Geometry.Sumter"
    },
    {
      "name": "Suwannee",
      "key": "Geometry.Suwannee"
    },
    {
      "name": "Taylor",
      "key": "Geometry.Taylor"
    },
    {
      "name": "Union",
      "key": "Geometry.Union"
    },
    {
      "name": "Volusia",
      "key": "Geometry.Volusia"
    },
    {
      "name": "Wakulla",
      "key": "Geometry.Wakulla"
    },
    {
      "name": "Walton",
      "key": "Geometry.Walton"
    },
    {
      "name": "Washington",
      "key": "Geometry.Washington"
    }
  ],
  "TX": [
    {
      "name": "Anderson",
      "key": "Geometry.Anderson"
    },
    {
      "name": "Andrews",
      "key": "Geometry.Andrews"
    },
    {
      "name": "Angelina",
      "key": "Geometry.Angelina"
    },
    {
      "name": "Aransas",
      "key": "Geometry.Aransas"
    },
    {
      "name": "Archer",
      "key": "Geometry.Archer"
    },
    {
      "name": "Armstrong",
      "key": "Geometry.Armstrong"
    },
    {
      "name": "Atascosa",
      "key": "Geometry.Atascosa"
    },
    {
      "name": "Austin",
      "key": "Geometry.Austin"
    },
    {
      "name": "Bailey",
      "key": "Geometry.Bailey"
    },
    {
      "name": "Bandera",
      "key": "Geometry.Bandera"
    },
    {
      "name": "Bastrop",
      "key": "Geometry.Bastrop"
    },
    {
      "name": "Baylor",
      "key": "Geometry.Baylor"
    },
    {
      "name": "Bee",
      "key": "Geometry.Bee"
    },
    {
      "name": "Bell",
      "key": "Geometry.Bell"
    },
    {
      "name": "Bexar",
      "key": "Geometry.Bexar"
    },
    {
      "name": "Blanco",
      "key": "Geometry.Blanco"
    },
    {
      "name": "Borden",
      "key": "Geometry.Borden"
    },
    {
      "name": "Bosque",
      "key": "Geometry.Bosque"
    },
    {
      "name": "Bowie",
      "key": "Geometry.Bowie"
    },
    {
      "name": "Brazoria",
      "key": "Geometry.Brazoria"
    },
    {
      "name": "Brazos",
      "key": "Geometry.Brazos"
    },
    {
      "name": "Brewster",
      "key": "Geometry.Brewster"
    },
    {
      "name": "Briscoe",
      "key": "Geometry.Briscoe"
    },
    {
      "name": "Brooks",
      "key": "Geometry.Brooks"
    },
    {
      "name": "Brown",
      "key": "Geometry.Brown"
    },
    {
      "name": "Burleson",
      "key": "Geometry.Burleson"
    },
    {
      "name": "Burnet",
      "key": "Geometry.Burnet"
    },
    {
      "name": "Caldwell",
      "key": "Geometry.Caldwell"
    },
    {
      "name": "Calhoun",
      "key": "Geometry.Calhoun"
    },
    {
      "name": "Callahan",
      "key": "Geometry.Callahan"
    },
    {
      "name": "Cameron",
      "key": "Geometry.Cameron"
    },
    {
      "name": "Camp",
      "key": "Geometry.Camp"
    },
    {
      "name": "Carson",
      "key": "Geometry.Carson"
    },
    {
      "name": "Cass",
      "key": "Geometry.Cass"
    },
    {
      "name": "Castro",
      "key": "Geometry.Castro"
    },
    {
      "name": "Chambers",
      "key": "Geometry.Chambers"
    },
    {
      "name": "Cherokee",
      "key": "Geometry.Cherokee"
    },
    {
      "name": "Childress",
      "key": "Geometry.Childress"
    },
    {
      "name": "Clay",
      "key": "Geometry.Clay"
    },
    {
      "name": "Cochran",
      "key": "Geometry.Cochran"
    },
    {
      "name": "Coke",
      "key": "Geometry.Coke"
    },
    {
      "name": "Coleman",
      "key": "Geometry.Coleman"
    },
    {
      "name": "Collin",
      "key": "Geometry.Collin"
    },
    {
      "name": "Collingsworth",
      "key": "Geometry.Collingsworth"
    },
    {
      "name": "Colorado",
      "key": "Geometry.Colorado"
    },
    {
      "name": "Comal",
      "key": "Geometry.Comal"
    },
    {
      "name": "Comanche",
      "key": "Geometry.Comanche"
    },
    {
      "name": "Concho",
      "key": "Geometry.Concho"
    },
    {
      "name": "Cooke",
      "key": "Geometry.Cooke"
    },
    {
      "name": "Coryell",
      "key": "Geometry.Coryell"
    },
    {
      "name": "Cottle",
      "key": "Geometry.Cottle"
    },
    {
      "name": "Crane",
      "key": "Geometry.Crane"
    },
    {
      "name": "Crockett",
      "key": "Geometry.Crockett"
    },
    {
      "name": "Crosby",
      "key": "Geometry.Crosby"
    },
    {
      "name": "Culberson",
      "key": "Geometry.Culberson"
    },
    {
      "name": "Dallam",
      "key": "Geometry.Dallam"
    },
    {
      "name": "Dallas",
      "key": "Geometry.Dallas"
    },
    {
      "name": "Dawson",
      "key": "Geometry.Dawson"
    },
    {
      "name": "Deaf Smith",
      "key": "Geometry.DeafSmith"
    },
    {
      "name": "Delta",
      "key": "Geometry.Delta"
    },
    {
      "name": "Denton",
      "key": "Geometry.Denton"
    },
    {
      "name": "DeWitt",
      "key": "Geometry.DeWitt"
    },
    {
      "name": "Dickens",
      "key": "Geometry.Dickens"
    },
    {
      "name": "Dimmit",
      "key": "Geometry.Dimmit"
    },
    {
      "name": "Donley",
      "key": "Geometry.Donley"
    },
    {
      "name": "Duval",
      "key": "Geometry.Duval"
    },
    {
      "name": "Eastland",
      "key": "Geometry.Eastland"
    },
    {
      "name": "Ector",
      "key": "Geometry.Ector"
    },
    {
      "name": "Edwards",
      "key": "Geometry.Edwards"
    },
    {
      "name": "Ellis",
      "key": "Geometry.Ellis"
    },
    {
      "name": "El Paso",
      "key": "Geometry.ElPaso"
    },
    {
      "name": "Erath",
      "key": "Geometry.Erath"
    },
    {
      "name": "Falls",
      "key": "Geometry.Falls"
    },
    {
      "name": "Fannin",
      "key": "Geometry.Fannin"
    },
    {
      "name": "Fayette",
      "key": "Geometry.Fayette"
    },
    {
      "name": "Fisher",
      "key": "Geometry.Fisher"
    },
    {
      "name": "Floyd",
      "key": "Geometry.Floyd"
    },
    {
      "name": "Foard",
      "key": "Geometry.Foard"
    },
    {
      "name": "Fort Bend",
      "key": "Geometry.FortBend"
    },
    {
      "name": "Franklin",
      "key": "Geometry.Franklin"
    },
    {
      "name": "Freestone",
      "key": "Geometry.Freestone"
    },
    {
      "name": "Frio",
      "key": "Geometry.Frio"
    },
    {
      "name": "Gaines",
      "key": "Geometry.Gaines"
    },
    {
      "name": "Galveston",
      "key": "Geometry.Galveston"
    },
    {
      "name": "Garza",
      "key": "Geometry.Garza"
    },
    {
      "name": "Gillespie",
      "key": "Geometry.Gillespie"
    },
    {
      "name": "Glasscock",
      "key": "Geometry.Glasscock"
    },
    {
      "name": "Goliad",
      "key": "Geometry.Goliad"
    },
    {
      "name": "Gonzales",
      "key": "Geometry.Gonzales"
    },
    {
      "name": "Gray",
      "key": "Geometry.Gray"
    },
    {
      "name": "Grayson",
      "key": "Geometry.Grayson"
    },
    {
      "name": "Gregg",
      "key": "Geometry.Gregg"
    },
    {
      "name": "Grimes",
      "key": "Geometry.Grimes"
    },
    {
      "name": "Guadalupe",
      "key": "Geometry.Guadalupe"
    },
    {
      "name": "Hale",
      "key": "Geometry.Hale"
    },
    {
      "name": "Hall",
      "key": "Geometry.Hall"
    },
    {
      "name": "Hamilton",
      "key": "Geometry.Hamilton"
    },
    {
      "name": "Hansford",
      "key": "Geometry.Hansford"
    },
    {
      "name": "Hardeman",
      "key": "Geometry.Hardeman"
    },
    {
      "name": "Hardin",
      "key": "Geometry.Hardin"
    },
    {
      "name": "Harris",
      "key": "Geometry.Harris"
    },
    {
      "name": "Harrison",
      "key": "Geometry.Harrison"
    },
    {
      "name": "Hartley",
      "key": "Geometry.Hartley"
    },
    {
      "name": "Haskell",
      "key": "Geometry.Haskell"
    },
    {
      "name": "Hays",
      "key": "Geometry.Hays"
    },
    {
      "name": "Hemphill",
      "key": "Geometry.Hemphill"
    },
    {
      "name": "Henderson",
      "key": "Geometry.Henderson"
    },
    {
      "name": "Hidalgo",
      "key": "Geometry.Hidalgo"
    },
    {
      "name": "Hill",
      "key": "Geometry.Hill"
    },
    {
      "name": "Hockley",
      "key": "Geometry.Hockley"
    },
    {
      "name": "Hood",
      "key": "Geometry.Hood"
    },
    {
      "name": "Hopkins",
      "key": "Geometry.Hopkins"
    },
    {
      "name": "Houston",
      "key": "Geometry.Houston"
    },
    {
      "name": "Howard",
      "key": "Geometry.Howard"
    },
    {
      "name": "Hudspeth",
      "key": "Geometry.Hudspeth"
    },
    {
      "name": "Hunt",
      "key": "Geometry.Hunt"
    },
    {
      "name": "Hutchinson",
      "key": "Geometry.Hutchinson"
    },
    {
      "name": "Irion",
      "key": "Geometry.Irion"
    },
    {
      "name": "Jack",
      "key": "Geometry.Jack"
    },
    {
      "name": "Jackson",
      "key": "Geometry.Jackson"
    },
    {
      "name": "Jasper",
      "key": "Geometry.Jasper"
    },
    {
      "name": "Jeff Davis",
      "key": "Geometry.JeffDavis"
    },
    {
      "name": "Jefferson",
      "key": "Geometry.Jefferson"
    },
    {
      "name": "Jim Hogg",
      "key": "Geometry.JimHogg"
    },
    {
      "name": "Jim Wells",
      "key": "Geometry.JimWells"
    },
    {
      "name": "Johnson",
      "key": "Geometry.Johnson"
    },
    {
      "name": "Jones",
      "key": "Geometry.Jones"
    },
    {
      "name": "Karnes",
      "key": "Geometry.Karnes"
    },
    {
      "name": "Kaufman",
      "key": "Geometry.Kaufman"
    },
    {
      "name": "Kendall",
      "key": "Geometry.Kendall"
    },
    {
      "name": "Kenedy",
      "key": "Geometry.Kenedy"
    },
    {
      "name": "Kent",
      "key": "Geometry.Kent"
    },
    {
      "name": "Kerr",
      "key": "Geometry.Kerr"
    },
    {
      "name": "Kimble",
      "key": "Geometry.Kimble"
    },
    {
      "name": "King",
      "key": "Geometry.King"
    },
    {
      "name": "Kinney",
      "key": "Geometry.Kinney"
    },
    {
      "name": "Kleberg",
      "key": "Geometry.Kleberg"
    },
    {
      "name": "Knox",
      "key": "Geometry.Knox"
    },
    {
      "name": "Lamar",
      "key": "Geometry.Lamar"
    },
    {
      "name": "Lamb",
      "key": "Geometry.Lamb"
    },
    {
      "name": "Lampasas",
      "key": "Geometry.Lampasas"
    },
    {
      "name": "La Salle",
      "key": "Geometry.LaSalle"
    },
    {
      "name": "Lavaca",
      "key": "Geometry.Lavaca"
    },
    {
      "name": "Lee",
      "key": "Geometry.Lee"
    },
    {
      "name": "Leon",
      "key": "Geometry.Leon"
    },
    {
      "name": "Liberty",
      "key": "Geometry.Liberty"
    },
    {
      "name": "Limestone",
      "key": "Geometry.Limestone"
    },
    {
      "name": "Lipscomb",
      "key": "Geometry.Lipscomb"
    },
    {
      "name": "Live Oak",
      "key": "Geometry.LiveOak"
    },
    {
      "name": "Llano",
      "key": "Geometry.Llano"
    },
    {
      "name": "Loving",
      "key": "Geometry.Loving"
    },
    {
      "name": "Lubbock",
      "key": "Geometry.Lubbock"
    },
    {
      "name": "Lynn",
      "key": "Geometry.Lynn"
    },
    {
      "name": "McCulloch",
      "key": "Geometry.McCulloch"
    },
    {
      "name": "McLennan",
      "key": "Geometry.McLennan"
    },
    {
      "name": "McMullen",
      "key": "Geometry.McMullen"
    },
    {
      "name": "Madison",
      "key": "Geometry.Madison"
    },
    {
      "name": "Marion",
      "key": "Geometry.Marion"
    },
    {
      "name": "Martin",
      "key": "Geometry.Martin"
    },
    {
      "name": "Mason",
      "key": "Geometry.Mason"
    },
    {
      "name": "Matagorda",
      "key": "Geometry.Matagorda"
    },
    {
      "name": "Maverick",
      "key": "Geometry.Maverick"
    },
    {
      "name": "Medina",
      "key": "Geometry.Medina"
    },
    {
      "name": "Menard",
      "key": "Geometry.Menard"
    },
    {
      "name": "Midland",
      "key": "Geometry.Midland"
    },
    {
      "name": "Milam",
      "key": "Geometry.Milam"
    },
    {
      "name": "Mills",
      "key": "Geometry.Mills"
    },
    {
      "name": "Mitchell",
      "key": "Geometry.Mitchell"
    },
    {
      "name": "Montague",
      "key": "Geometry.Montague"
    },
    {
      "name": "Montgomery",
      "key": "Geometry.Montgomery"
    },
    {
      "name": "Moore",
      "key": "Geometry.Moore"
    },
    {
      "name": "Morris",
      "key": "Geometry.Morris"
    },
    {
      "name": "Motley",
      "key": "Geometry.Motley"
    },
    {
      "name": "Nacogdoches",
      "key": "Geometry.Nacogdoches"
    },
    {
      "name": "Navarro",
      "key": "Geometry.Navarro"
    },
    {
      "name": "Newton",
      "key": "Geometry.Newton"
    },
    {
      "name": "Nolan",
      "key": "Geometry.Nolan"
    },
    {
      "name": "Nueces",
      "key": "Geometry.Nueces"
    },
    {
      "name": "Ochiltree",
      "key": "Geometry.Ochiltree"
    },
    {
      "name": "Oldham",
      "key": "Geometry.Oldham"
    },
    {
      "name": "Orange",
      "key": "Geometry.Orange"
    },
    {
      "name": "Palo Pinto",
      "key": "Geometry.PaloPinto"
    },
    {
      "name": "Panola",
      "key": "Geometry.Panola"
    },
    {
      "name": "Parker",
      "key": "Geometry.Parker"
    },
    {
      "name": "Parmer",
      "key": "Geometry.Parmer"
    },
    {
      "name": "Pecos",
      "key": "Geometry.Pecos"
    },
    {
      "name": "Polk",
      "key": "Geometry.Polk"
    },
    {
      "name": "Potter",
      "key": "Geometry.Potter"
    },
    {
      "name": "Presidio",
      "key": "Geometry.Presidio"
    },
    {
      "name": "Rains",
      "key": "Geometry.Rains"
    },
    {
      "name": "Randall",
      "key": "Geometry.Randall"
    },
    {
      "name": "Reagan",
      "key": "Geometry.Reagan"
    },
    {
      "name": "Real",
      "key": "Geometry.Real"
    },
    {
      "name": "Red River",
      "key": "Geometry.RedRiver"
    },
    {
      "name": "Reeves",
      "key": "Geometry.Reeves"
    },
    {
      "name": "Refugio",
      "key": "Geometry.Refugio"
    },
    {
      "name": "Roberts",
      "key": "Geometry.Roberts"
    },
    {
      "name": "Robertson",
      "key": "Geometry.Robertson"
    },
    {
      "name": "Rockwall",
      "key": "Geometry.Rockwall"
    },
    {
      "name": "Runnels",
      "key": "Geometry.Runnels"
    },
    {
      "name": "Rusk",
      "key": "Geometry.Rusk"
    },
    {
      "name": "Sabine",
      "key": "Geometry.Sabine"
    },
    {
      "name": "San Augustine",
      "key": "Geometry.SanAugustine"
    },
    {
      "name": "San Jacinto",
      "key": "Geometry.SanJacinto"
    },
    {
      "name": "San Patricio",
      "key": "Geometry.SanPatricio"
    },
    {
      "name": "San Saba",
      "key": "Geometry.SanSaba"
    },
    {
      "name": "Schleicher",
      "key": "Geometry.Schleicher"
    },
    {
      "name": "Scurry",
      "key": "Geometry.Scurry"
    },
    {
      "name": "Shackelford",
      "key": "Geometry.Shackelford"
    },
    {
      "name": "Shelby",
      "key": "Geometry.Shelby"
    },
    {
      "name": "Sherman",
      "key": "Geometry.Sherman"
    },
    {
      "name": "Smith",
      "key": "Geometry.Smith"
    },
    {
      "name": "Somervell",
      "key": "Geometry.Somervell"
    },
    {
      "name": "Starr",
      "key": "Geometry.Starr"
    },
    {
      "name": "Stephens",
      "key": "Geometry.Stephens"
    },
    {
      "name": "Sterling",
      "key": "Geometry.Sterling"
    },
    {
      "name": "Stonewall",
      "key": "Geometry.Stonewall"
    },
    {
      "name": "Sutton",
      "key": "Geometry.Sutton"
    },
    {
      "name": "Swisher",
      "key": "Geometry.Swisher"
    },
    {
      "name": "Tarrant",
      "key": "Geometry.Tarrant"
    },
    {
      "name": "Taylor",
      "key": "Geometry.Taylor"
    },
    {
      "name": "Terrell",
      "key": "Geometry.Terrell"
    },
    {
      "name": "Terry",
      "key": "Geometry.Terry"
    },
    {
      "name": "Throckmorton",
      "key": "Geometry.Throckmorton"
    },
    {
      "name": "Titus",
      "key": "Geometry.Titus"
    },
    {
      "name": "Tom Green",
      "key": "Geometry.TomGreen"
    },
    {
      "name": "Travis",
      "key": "Geometry.Travis"
    },
    {
      "name": "Trinity",
      "key": "Geometry.Trinity"
    },
    {
      "name": "Tyler",
      "key": "Geometry.Tyler"
    },
    {
      "name": "Upshur",
      "key": "Geometry.Upshur"
    },
    {
      "name": "Upton",
      "key": "Geometry.Upton"
    },
    {
      "name": "Uvalde",
      "key": "Geometry.Uvalde"
    },
    {
      "name": "Val Verde",
      "key": "Geometry.ValVerde"
    },
    {
      "name": "Van Zandt",
      "key": "Geometry.VanZandt"
    },
    {
      "name": "Victoria",
      "key": "Geometry.Victoria"
    },
    {
      "name": "Walker",
      "key": "Geometry.Walker"
    },
    {
      "name": "Waller",
      "key": "Geometry.Waller"
    },
    {
      "name": "Ward",
      "key": "Geometry.Ward"
    },
    {
      "name": "Washington",
      "key": "Geometry.Washington"
    },
    {
      "name": "Webb",
      "key": "Geometry.Webb"
    },
    {
      "name": "Wharton",
      "key": "Geometry.Wharton"
    },
    {
      "name": "Wheeler",
      "key": "Geometry.Wheeler"
    },
    {
      "name": "Wichita",
      "key": "Geometry.Wichita"
    },
    {
      "name": "Wilbarger",
      "key": "Geometry.Wilbarger"
    },
    {
      "name": "Willacy",
      "key": "Geometry.Willacy"
    },
    {
      "name": "Williamson",
      "key": "Geometry.Williamson"
    },
    {
      "name": "Wilson",
      "key": "Geometry.Wilson"
    },
    {
      "name": "Winkler",
      "key": "Geometry.Winkler"
    },
    {
      "name": "Wise",
      "key": "Geometry.Wise"
    },
    {
      "name": "Wood",
      "key": "Geometry.Wood"
    },
    {
      "name": "Yoakum",
      "key": "Geometry.Yoakum"
    },
    {
      "name": "Young",
      "key": "Geometry.Young"
    },
    {
      "name": "Zapata",
      "key": "Geometry.Zapata"
    },
    {
      "name": "Zavala",
      "key": "Geometry.Zavala"
    }
  ]
}